<?xml version="1.0" encoding="UTF-8"?>
<objects serializationModel="Studio.02.03.00">
	<object class="AudioFile" id="{11500d8f-562f-4fd6-a690-0d91628556db}">
		<property name="assetPath">
			<value>mode/furnace6.ogg</value>
		</property>
		<property name="frequencyInKHz">
			<value>44.0999985</value>
		</property>
		<property name="channelCount">
			<value>1</value>
		</property>
		<property name="length">
			<value>1.1034920634920635</value>
		</property>
		<relationship name="masterAssetFolder">
			<destination>{64593b19-ba3c-45c9-81dc-1bf0efdf6d8b}</destination>
		</relationship>
	</object>
</objects>
